{
  "title": "STOP_SOUND",
  "breadcrumbs": [
    "Native Reference",
    "AUDIOAPI",
    "STOP_SOUND"
  ],
  "content": "0xA3B0C41BA5CC0BB50xCD7F4030// StopSound\nvoid STOP_SOUND(int soundId);Parameters:soundId: The sound id to stopStops the sound from currently playing, there isn't a way to resume a sound\nafter stopping it.",
  "codeBlocks": [
    "// StopSound\nvoid STOP_SOUND(int soundId);",
    "-- Example usage for STOP_SOUND\nStopSound(1)"
  ],
  "urls": [
    "https://docs.fivem.net/docs/",
    "https://docs.fivem.net/natives/",
    "https://github.com/citizenfx/natives/edit/master/AUDIO/StopSound.md",
    "https://www.rockstargames.com/privacy",
    "https://www.rockstargames.com/cookies"
  ],
  "tags": [
    "client"
  ]
}